pysondb/__init__.py
pysondb/__main__.py
pysondb/cli.py
pysondb/db.py
pysondb/db_types.py
pysondb/errors.py
pysondb/utils.py
pysondb_v2-2.2.0.dist-info/LICENSE
pysondb_v2-2.2.0.dist-info/METADATA
pysondb_v2-2.2.0.dist-info/WHEEL
pysondb_v2-2.2.0.dist-info/entry_points.txt
pysondb_v2-2.2.0.dist-info/top_level.txt
pysondb_v2-2.2.0.dist-info/RECORD
