Metadata-Version: 2.1
Name: pysondb-v2
Version: 2.2.0
Summary: A Simple, Lightweight, Efficent JSON based database for Python.
Home-page: https://github.com/pysonDB/pysonDB-v2
Author: Adwaith Rajesh
Author-email: adwaithrajesh3180@gmail.com
License: MIT
Classifier: License :: OSI Approved :: MIT License
Classifier: Programming Language :: Python :: 3
Classifier: Programming Language :: Python :: 3 :: Only
Classifier: Programming Language :: Python :: 3.7
Classifier: Programming Language :: Python :: 3.8
Classifier: Programming Language :: Python :: 3.9
Classifier: Programming Language :: Python :: 3.10
Requires-Python: >=3.7.0
License-File: LICENSE
Provides-Extra: ujson
Requires-Dist: ujson==5.2.0; extra == "ujson"
Provides-Extra: pretttytable
Requires-Dist: prettytable==3.3.0; extra == "pretttytable"
Provides-Extra: all
Requires-Dist: ujson==5.2.0; extra == "all"
Requires-Dist: prettytable==3.3.0; extra == "all"
